fasvaorm/__init__.py
fasvaorm/models.py
fasvaorm/schema.py
fasvaorm/signal.py
fasvaorm/timebased_models.py
fasvaorm/utils.py
tests/__init__.py
tests/base.py
tests/test_marshalling.py
tests/test_model_module.py
tests/test_models.py
tests/test_numpy_support.py
tests/test_orm.py
tests/test_serialization.py
fasvaorm-0.8.3.dist-info/LICENSE
fasvaorm-0.8.3.dist-info/METADATA
fasvaorm-0.8.3.dist-info/WHEEL
fasvaorm-0.8.3.dist-info/entry_points.txt
fasvaorm-0.8.3.dist-info/top_level.txt
fasvaorm-0.8.3.dist-info/RECORD
