Metadata-Version: 2.1
Name: fasvaorm
Version: 0.8.3
Summary: fasvaorm is a ORM to access the database used within FASva.
Home-page: UNKNOWN
Author: Lars Klitzke
Author-email: Lars.Klitzke@hs-emden-leer.de
License: GNU GPLv3
Platform: UNKNOWN
Classifier: Programming Language :: Python :: 3
Classifier: Programming Language :: Python :: 3.5
Classifier: Programming Language :: Unix Shell
Classifier: Intended Audience :: Science/Research
Classifier: Intended Audience :: Information Technology
Classifier: Intended Audience :: Manufacturing
Classifier: License :: Other/Proprietary License
Classifier: Operating System :: POSIX
Classifier: Topic :: Scientific/Engineering :: Information Analysis
Requires-Dist: pymysql
Requires-Dist: sqlalchemy
Requires-Dist: sqlalchemy-utils
Requires-Dist: marshmallow (==3.0.0b13)
Requires-Dist: pymodconf
Requires-Dist: numpy
